{
  "metrics": [
    {
      "rmse": 3.2402172088623047,
      "mae": 2.067145586013794,
      "bias": -0.0165866669267416,
      "nrmse": 0.41696409516550187,
      "r2": 0.8261409401893616,
      "corr": 0.9334440766655163,
      "fit_slope": 0.6729255801265857,
      "fit_intercept": -0.016480299017366785,
      "forward_residual_rmse": 0.0005931431660428643,
      "case": "no_noise_improved",
      "noise_scale": 0.0,
      "best_val_loss": 0.924394252044814,
      "num_train_windows": 67,
      "num_test_windows": 16,
      "training_mode": "independent",
      "epochs_completed": 16
    },
    {
      "rmse": 6.208236217498779,
      "mae": 4.3810906410217285,
      "bias": 0.12048731744289398,
      "nrmse": 0.7989006384889802,
      "r2": 0.361757755279541,
      "corr": 0.6065886191882384,
      "fit_slope": 0.3211533494786631,
      "fit_intercept": 0.12070814643255817,
      "forward_residual_rmse": 0.002942777704447508,
      "case": "very_low_noise_improved",
      "noise_scale": 0.05,
      "best_val_loss": 2.5665378740855624,
      "num_train_windows": 67,
      "num_test_windows": 16,
      "training_mode": "independent",
      "epochs_completed": 16
    },
    {
      "rmse": 7.404013633728027,
      "mae": 5.278472900390625,
      "bias": -0.1913633793592453,
      "nrmse": 0.9527780535627788,
      "r2": 0.09221398830413818,
      "corr": 0.3373353095141055,
      "fit_slope": 0.16265020936054267,
      "fit_intercept": -0.1910909311815266,
      "forward_residual_rmse": 0.005694839172065258,
      "case": "low_noise_improved",
      "noise_scale": 0.1,
      "best_val_loss": 2.826556899717876,
      "num_train_windows": 67,
      "num_test_windows": 16,
      "training_mode": "independent",
      "epochs_completed": 16
    },
    {
      "rmse": 8.323192596435547,
      "mae": 5.823225498199463,
      "bias": -0.2116667628288269,
      "nrmse": 1.0710616746213424,
      "r2": -0.14717316627502441,
      "corr": -0.07646662638493382,
      "fit_slope": -0.02399232171333797,
      "fit_intercept": -0.2113336557151036,
      "forward_residual_rmse": 0.014515089802443981,
      "case": "reference_noise_improved",
      "noise_scale": 0.25,
      "best_val_loss": 3.948539844581059,
      "num_train_windows": 67,
      "num_test_windows": 16,
      "training_mode": "independent",
      "epochs_completed": 16
    },
    {
      "rmse": 1.4878474473953247,
      "mae": 1.0367708206176758,
      "bias": -0.0034654210321605206,
      "nrmse": 0.3417131521094659,
      "r2": 0.8832321166992188,
      "corr": 0.9434356960473266,
      "fit_slope": 0.8120551697462046,
      "fit_intercept": -0.003850728396632133,
      "forward_residual_rmse": 0.0002531234349589795,
      "case": "tiny_clean_overfit",
      "noise_scale": 0.0,
      "num_train_windows": 8,
      "num_test_windows": 8,
      "training_mode": "diagnostic"
    }
  ],
  "history": {
    "no_noise_improved": [
      {
        "epoch": 1,
        "loss": 2.7081253581972264,
        "loss_state": 0.9802597231829344,
        "loss_phys": 32.786188680734206,
        "loss_corr": 0.8649519326081917,
        "loss_amp": 2.8962527255513777,
        "loss_tv": 0.8698252848724821,
        "lambda_fwd": 0.003333333333333333,
        "val_loss": 4.478990946497236,
        "val_state": 1.7928936524050576,
        "val_phys": 20.91224534170968,
        "val_corr": 1.5574469906943185,
        "val_amp": 4.175287817205701
      },
      {
        "epoch": 2,
        "loss": 2.380827535444231,
        "loss_state": 0.9096966056681391,
        "loss_phys": 7.131119809933563,
        "loss_corr": 0.7966642379760742,
        "loss_amp": 2.4319318025859435,
        "loss_tv": 1.6292705108870322,
        "lambda_fwd": 0.006666666666666666,
        "val_loss": 4.01473776783262,
        "val_state": 1.6369550973176956,
        "val_phys": 4.351116384778704,
        "val_corr": 1.1543988840920585,
        "val_amp": 3.945875380720411
      },
      {
        "epoch": 3,
        "loss": 1.8447312863905039,
        "loss_state": 0.7652569522163761,
        "loss_phys": 3.1501512011485313,
        "loss_corr": 0.5286095213534227,
        "loss_amp": 1.6883477292843718,
        "loss_tv": 2.5717464560893046,
        "lambda_fwd": 0.01,
        "val_loss": 2.7487467399665286,
        "val_state": 1.2655190165553774,
        "val_phys": 6.368964297430856,
        "val_corr": 0.4189573185784476,
        "val_amp": 2.2025629792894637
      },
      {
        "epoch": 4,
        "loss": 1.1170283177895333,
        "loss_state": 0.5189005267709049,
        "loss_phys": 2.8593060810174515,
        "loss_corr": 0.25328490627345757,
        "loss_amp": 0.7474306546040436,
        "loss_tv": 3.3878119098606394,
        "lambda_fwd": 0.013333333333333332,
        "val_loss": 1.7696393919842583,
        "val_state": 0.868388654930251,
        "val_phys": 0.9669197159154075,
        "val_corr": 0.15509450435638428,
        "val_amp": 1.357538172176906
      },
      {
        "epoch": 5,
        "loss": 0.7896359037997117,
        "loss_state": 0.3643557300318533,
        "loss_phys": 1.1696373419975168,
        "loss_corr": 0.15716060951574526,
        "loss_amp": 0.5871083026946481,
        "loss_tv": 3.2765395463402593,
        "lambda_fwd": 0.016666666666666666,
        "val_loss": 1.4028701782226562,
        "val_state": 0.6909620378698621,
        "val_phys": 0.836007799421038,
        "val_corr": 0.08192886625017438,
        "val_amp": 1.092051386833191
      },
      {
        "epoch": 6,
        "loss": 0.6433782817712471,
        "loss_state": 0.30084094605339107,
        "loss_phys": 0.9014960865476238,
        "loss_corr": 0.10764640391762577,
        "loss_amp": 0.4718306414894204,
        "loss_tv": 2.4381867024435926,
        "lambda_fwd": 0.02,
        "val_loss": 1.2791598524366106,
        "val_state": 0.6270837336778641,
        "val_phys": 0.8395681210926601,
        "val_corr": 0.050529692854200094,
        "val_amp": 1.021222553082875
      },
      {
        "epoch": 7,
        "loss": 0.5584435260562755,
        "loss_state": 0.27212695643972995,
        "loss_phys": 0.6828860978582012,
        "loss_corr": 0.0907938756159882,
        "loss_amp": 0.36391139208380857,
        "loss_tv": 1.837935835567873,
        "lambda_fwd": 0.02,
        "val_loss": 1.19466646867139,
        "val_state": 0.5906575976737908,
        "val_phys": 0.7428582736424038,
        "val_corr": 0.03695058822631836,
        "val_amp": 0.9418870827981404
      },
      {
        "epoch": 8,
        "loss": 0.5096382171805225,
        "loss_state": 0.25503956092827357,
        "loss_phys": 0.6344433498026719,
        "loss_corr": 0.08098951916196453,
        "loss_amp": 0.29980633152064995,
        "loss_tv": 1.5124677366285182,
        "lambda_fwd": 0.02,
        "val_loss": 1.116461074778012,
        "val_state": 0.561273027743612,
        "val_phys": 0.7584666460752487,
        "val_corr": 0.030540083135877336,
        "val_amp": 0.833577173096793
      },
      {
        "epoch": 9,
        "loss": 0.4727711121537792,
        "loss_state": 0.24262711183348698,
        "loss_phys": 0.6197043408208819,
        "loss_corr": 0.07272160231177487,
        "loss_amp": 0.24828808387713647,
        "loss_tv": 1.3344974962633047,
        "lambda_fwd": 0.02,
        "val_loss": 1.0576906991856438,
        "val_state": 0.5384807517485959,
        "val_phys": 0.8225262122494834,
        "val_corr": 0.02721937213625227,
        "val_amp": 0.7507298343947956
      },
      {
        "epoch": 10,
        "loss": 0.4458783191086641,
        "loss_state": 0.23385614790578388,
        "loss_phys": 0.568439057513849,
        "loss_corr": 0.06672818269302595,
        "loss_amp": 0.211945267143979,
        "loss_tv": 1.2327849028715447,
        "lambda_fwd": 0.02,
        "val_loss": 1.013039472912039,
        "val_state": 0.5221960794712815,
        "val_phys": 0.7760909668036869,
        "val_corr": 0.025428380284990584,
        "val_amp": 0.6882302473698344
      },
      {
        "epoch": 11,
        "loss": 0.4259932708384386,
        "loss_state": 0.22776315216697865,
        "loss_phys": 0.5021896936110596,
        "loss_corr": 0.06152009608140632,
        "loss_amp": 0.1857737460687979,
        "loss_tv": 1.1658506553564498,
        "lambda_fwd": 0.02,
        "val_loss": 0.9782504066824913,
        "val_state": 0.5103909745812416,
        "val_phys": 0.6672392040491104,
        "val_corr": 0.02464491980416434,
        "val_amp": 0.6393492243119648
      },
      {
        "epoch": 12,
        "loss": 0.41153792925735017,
        "loss_state": 0.22342501425031405,
        "loss_phys": 0.43742765286075536,
        "loss_corr": 0.05685874241501538,
        "loss_amp": 0.16827271422788279,
        "loss_tv": 1.1240757605922755,
        "lambda_fwd": 0.02,
        "val_loss": 0.9545865931681224,
        "val_state": 0.5017329433134624,
        "val_phys": 0.6385313017027718,
        "val_corr": 0.02417597600391933,
        "val_amp": 0.6061536659087453
      },
      {
        "epoch": 13,
        "loss": 0.40231480883128606,
        "loss_state": 0.2204321174701648,
        "loss_phys": 0.41656748950481415,
        "loss_corr": 0.05339695802375452,
        "loss_amp": 0.1573546887444916,
        "loss_tv": 1.0978111188803146,
        "lambda_fwd": 0.02,
        "val_loss": 0.9393037302153451,
        "val_state": 0.4960491896740028,
        "val_phys": 0.628541539822306,
        "val_corr": 0.023891704423086985,
        "val_amp": 0.5845870567219598
      },
      {
        "epoch": 14,
        "loss": 0.3968082461784135,
        "loss_state": 0.21856700595635087,
        "loss_phys": 0.4120569411498397,
        "loss_corr": 0.05119104794601896,
        "loss_amp": 0.15083711421979007,
        "loss_tv": 1.0815333946427304,
        "lambda_fwd": 0.02,
        "val_loss": 0.92988043065582,
        "val_state": 0.4929212400955813,
        "val_phys": 0.6226474493741989,
        "val_corr": 0.02388880934034075,
        "val_amp": 0.5692154797060149
      },
      {
        "epoch": 15,
        "loss": 0.3936675740266914,
        "loss_state": 0.21755100608761632,
        "loss_phys": 0.4074402518236815,
        "loss_corr": 0.049560130532108136,
        "loss_amp": 0.14738966446759097,
        "loss_tv": 1.0731139432138472,
        "lambda_fwd": 0.02,
        "val_loss": 0.925510830112866,
        "val_state": 0.4914981116141592,
        "val_phys": 0.6199158195938382,
        "val_corr": 0.023910880088806152,
        "val_amp": 0.561927793281419
      },
      {
        "epoch": 16,
        "loss": 0.39232031956537444,
        "loss_state": 0.21712570670825332,
        "loss_phys": 0.40559047327112796,
        "loss_corr": 0.04869334733308251,
        "loss_amp": 0.1460165206287334,
        "loss_tv": 1.0699435472488403,
        "lambda_fwd": 0.02,
        "val_loss": 0.924394252044814,
        "val_state": 0.4911430573889187,
        "val_phys": 0.6191924980708531,
        "val_corr": 0.023922204971313477,
        "val_amp": 0.560018281851496
      }
    ],
    "very_low_noise_improved": [
      {
        "epoch": 1,
        "loss": 2.6315115708023753,
        "loss_state": 1.010005433612795,
        "loss_phys": 1.0155807057423378,
        "loss_corr": 0.8784793917812518,
        "loss_amp": 2.8316823866829943,
        "loss_tv": 0.6959119474709924,
        "lambda_fwd": 0.003333333333333333,
        "val_loss": 4.413720211812428,
        "val_state": 1.8761350512504578,
        "val_phys": 1.1453572937420435,
        "val_corr": 1.5888971260615758,
        "val_amp": 3.729787622179304
      },
      {
        "epoch": 2,
        "loss": 2.4929411037644345,
        "loss_state": 1.0005112752985599,
        "loss_phys": 1.0035411386347528,
        "loss_corr": 0.8654910859776966,
        "loss_amp": 2.4190555873201856,
        "loss_tv": 1.1985795853742913,
        "lambda_fwd": 0.006666666666666666,
        "val_loss": 4.24758717417717,
        "val_state": 1.8374787781919752,
        "val_phys": 1.1305094787052699,
        "val_corr": 1.4666874153273446,
        "val_amp": 3.4789190334933147
      },
      {
        "epoch": 3,
        "loss": 2.334716633184632,
        "loss_state": 0.9812504666954723,
        "loss_phys": 0.9765491752482173,
        "loss_corr": 0.8149599530803624,
        "loss_amp": 2.028018479916587,
        "loss_tv": 1.8182728290557861,
        "lambda_fwd": 0.01,
        "val_loss": 3.9201908111572266,
        "val_state": 1.7360647767782211,
        "val_phys": 1.0869872740336828,
        "val_corr": 1.1722385883331299,
        "val_amp": 3.177772973264967
      },
      {
        "epoch": 4,
        "loss": 2.0756476192332025,
        "loss_state": 0.937413609294749,
        "loss_phys": 0.9089364222626188,
        "loss_corr": 0.674367975832811,
        "loss_amp": 1.5161595842731532,
        "loss_tv": 2.497877811318013,
        "lambda_fwd": 0.013333333333333332,
        "val_loss": 3.206886683191572,
        "val_state": 1.532662297998156,
        "val_phys": 0.9995590788977486,
        "val_corr": 0.720042714050838,
        "val_amp": 2.2608610689640045
      },
      {
        "epoch": 5,
        "loss": 1.8615620865750668,
        "loss_state": 0.9054399070455067,
        "loss_phys": 0.8315648614470639,
        "loss_corr": 0.5382424254915608,
        "loss_amp": 1.0925943095292618,
        "loss_tv": 2.9179431609253386,
        "lambda_fwd": 0.016666666666666666,
        "val_loss": 2.855892777442932,
        "val_state": 1.4034159566674913,
        "val_phys": 0.9436507054737636,
        "val_corr": 0.5592679807118007,
        "val_amp": 1.889922857284546
      },
      {
        "epoch": 6,
        "loss": 1.7748804946443928,
        "loss_state": 0.8740220941714386,
        "loss_phys": 0.8063127149396868,
        "loss_corr": 0.48125156893658994,
        "loss_amp": 1.0103405473837213,
        "loss_tv": 2.4346361694051257,
        "lambda_fwd": 0.02,
        "val_loss": 2.789820202759334,
        "val_state": 1.3555654627936227,
        "val_phys": 0.9319678885596139,
        "val_corr": 0.5161060605730329,
        "val_amp": 1.9426152663571494
      },
      {
        "epoch": 7,
        "loss": 1.722865202533665,
        "loss_state": 0.8460180394685091,
        "loss_phys": 0.8015149440338363,
        "loss_corr": 0.4547073485246345,
        "loss_amp": 1.0040044989158858,
        "loss_tv": 1.9429836735796573,
        "lambda_fwd": 0.02,
        "val_loss": 2.7283558590071544,
        "val_state": 1.323631192956652,
        "val_phys": 0.9239835568836757,
        "val_corr": 0.49155282974243164,
        "val_amp": 1.922607639006206
      },
      {
        "epoch": 8,
        "loss": 1.6849955071264238,
        "loss_state": 0.8310900828731593,
        "loss_phys": 0.7965391011380437,
        "loss_corr": 0.43719566046302,
        "loss_amp": 0.9703369069455275,
        "loss_tv": 1.698170306077644,
        "lambda_fwd": 0.02,
        "val_loss": 2.6665699822562083,
        "val_state": 1.2974383703299932,
        "val_phys": 0.9159453511238098,
        "val_corr": 0.47582868167332243,
        "val_amp": 1.8639433213642664
      },
      {
        "epoch": 9,
        "loss": 1.6549185763544112,
        "loss_state": 0.8197421351475502,
        "loss_phys": 0.7920964511472788,
        "loss_corr": 0.4257711367820626,
        "loss_amp": 0.9385922773560481,
        "loss_tv": 1.5443322640746386,
        "lambda_fwd": 0.02,
        "val_loss": 2.6304254872458324,
        "val_state": 1.2809875990663255,
        "val_phys": 0.909078231879643,
        "val_corr": 0.46747611250196186,
        "val_amp": 1.8345703120742525
      },
      {
        "epoch": 10,
        "loss": 1.6316257323791732,
        "loss_state": 0.8098284237420381,
        "loss_phys": 0.78864545964483,
        "loss_corr": 0.4185192780708199,
        "loss_amp": 0.9180355401181463,
        "loss_tv": 1.4374181032180786,
        "lambda_fwd": 0.02,
        "val_loss": 2.6088587045669556,
        "val_state": 1.2704793470246452,
        "val_phys": 0.9043892621994019,
        "val_corr": 0.4638077872140067,
        "val_amp": 1.819233545235225
      },
      {
        "epoch": 11,
        "loss": 1.612958312034607,
        "loss_state": 0.801793585962324,
        "loss_phys": 0.7862287830950608,
        "loss_corr": 0.41330023310077724,
        "loss_amp": 0.9013895170012517,
        "loss_tv": 1.36400133282391,
        "lambda_fwd": 0.02,
        "val_loss": 2.592969698565347,
        "val_state": 1.2628315559455328,
        "val_phys": 0.9004124913896833,
        "val_corr": 0.46182080677577425,
        "val_amp": 1.8067814367158073
      },
      {
        "epoch": 12,
        "loss": 1.5986024425990546,
        "loss_state": 0.7957508194802413,
        "loss_phys": 0.7841394952873686,
        "loss_corr": 0.4094216503314118,
        "loss_amp": 0.8877840749363402,
        "loss_tv": 1.3166978145713237,
        "lambda_fwd": 0.02,
        "val_loss": 2.581119477748871,
        "val_state": 1.2573438159057073,
        "val_phys": 0.8971597041402545,
        "val_corr": 0.4605813537325178,
        "val_amp": 1.7961882948875427
      },
      {
        "epoch": 13,
        "loss": 1.5881597017174336,
        "loss_state": 0.7914510983139721,
        "loss_phys": 0.7825054624187413,
        "loss_corr": 0.4066653981137632,
        "loss_amp": 0.8773486569746217,
        "loss_tv": 1.2870826641125466,
        "lambda_fwd": 0.02,
        "val_loss": 2.5732532228742326,
        "val_state": 1.253715183053698,
        "val_phys": 0.8947404963629586,
        "val_corr": 0.459726231438773,
        "val_amp": 1.7891346322638648
      },
      {
        "epoch": 14,
        "loss": 1.5813938717343914,
        "loss_state": 0.7886643721096551,
        "loss_phys": 0.7813894366150471,
        "loss_corr": 0.4048755631518008,
        "loss_amp": 0.8705996346117845,
        "loss_tv": 1.2696501043305468,
        "lambda_fwd": 0.02,
        "val_loss": 2.568975576332637,
        "val_state": 1.2517148511750358,
        "val_phys": 0.89333176612854,
        "val_corr": 0.45931361402784077,
        "val_amp": 1.7853878374610628
      },
      {
        "epoch": 15,
        "loss": 1.577639771931207,
        "loss_state": 0.787146865876753,
        "loss_phys": 0.7807547841499101,
        "loss_corr": 0.40389586028768054,
        "loss_amp": 0.866698431434916,
        "loss_tv": 1.2606473929846465,
        "lambda_fwd": 0.02,
        "val_loss": 2.5670216849872043,
        "val_state": 1.2508146933146886,
        "val_phys": 0.892640403338841,
        "val_corr": 0.45915792669568745,
        "val_amp": 1.783579402736255
      },
      {
        "epoch": 16,
        "loss": 1.5760786995958926,
        "loss_state": 0.7865419036416865,
        "loss_phys": 0.780478918730323,
        "loss_corr": 0.4034788893229926,
        "loss_amp": 0.8649562530553163,
        "loss_tv": 1.2571383198695396,
        "lambda_fwd": 0.02,
        "val_loss": 2.5665378740855624,
        "val_state": 1.2505908225263869,
        "val_phys": 0.8924613765307835,
        "val_corr": 0.4591115542820522,
        "val_amp": 1.7831445229904992
      }
    ],
    "low_noise_improved": [
      {
        "epoch": 1,
        "loss": 2.5728794460865987,
        "loss_state": 0.9976631496379624,
        "loss_phys": 0.9926707620051369,
        "loss_corr": 0.8843130709520027,
        "loss_amp": 2.6920959816050174,
        "loss_tv": 1.5309600509814363,
        "lambda_fwd": 0.003333333333333333,
        "val_loss": 4.229788426842008,
        "val_state": 1.8887599004166467,
        "val_phys": 1.1026479687009538,
        "val_corr": 1.5162257637296404,
        "val_amp": 3.12618065731866
      },
      {
        "epoch": 2,
        "loss": 2.3795624935804907,
        "loss_state": 1.0411853834764282,
        "loss_phys": 0.9892914295196533,
        "loss_corr": 0.9082266572696059,
        "loss_amp": 1.7945595712804083,
        "loss_tv": 3.531994897927811,
        "lambda_fwd": 0.006666666666666666,
        "val_loss": 4.018256987844195,
        "val_state": 1.9338363856077194,
        "val_phys": 1.0985691887991769,
        "val_corr": 1.35035525900977,
        "val_amp": 2.3487725598471507
      },
      {
        "epoch": 3,
        "loss": 2.314996568124686,
        "loss_state": 1.0670245796886844,
        "loss_phys": 0.9836712186016253,
        "loss_corr": 0.9115148996239277,
        "loss_amp": 1.435746751614471,
        "loss_tv": 4.444740156629193,
        "lambda_fwd": 0.01,
        "val_loss": 3.9238486630576,
        "val_state": 1.886763606752668,
        "val_phys": 1.088118348802839,
        "val_corr": 1.3117942128862654,
        "val_amp": 2.2962605910641805
      },
      {
        "epoch": 4,
        "loss": 2.2431096585828865,
        "loss_state": 1.0304670818706057,
        "loss_phys": 0.9680194570057428,
        "loss_corr": 0.8683726751982276,
        "loss_amp": 1.4120411979618357,
        "loss_tv": 3.7792903558531803,
        "lambda_fwd": 0.013333333333333332,
        "val_loss": 3.697093631540026,
        "val_state": 1.7800025939941406,
        "val_phys": 1.062427009854998,
        "val_corr": 1.1653427055903844,
        "val_amp": 2.2099467324359074
      },
      {
        "epoch": 5,
        "loss": 2.1445687048470794,
        "loss_state": 1.0039103124568711,
        "loss_phys": 0.9367695014868209,
        "loss_corr": 0.7951527389127817,
        "loss_amp": 1.2805951602423369,
        "loss_tv": 3.660754890584234,
        "lambda_fwd": 0.016666666666666666,
        "val_loss": 3.3659942150115967,
        "val_state": 1.6475164677415575,
        "val_phys": 1.026268550327846,
        "val_corr": 0.8927858471870422,
        "val_amp": 2.0314165694372996
      },
      {
        "epoch": 6,
        "loss": 2.0524962606714734,
        "loss_state": 0.9774391784596799,
        "loss_phys": 0.9056304283996126,
        "loss_corr": 0.7276210535818072,
        "loss_amp": 1.1653139537839747,
        "loss_tv": 3.443396611000175,
        "lambda_fwd": 0.02,
        "val_loss": 3.124378059591566,
        "val_state": 1.5337292424270086,
        "val_phys": 1.004700779914856,
        "val_corr": 0.710280043738229,
        "val_amp": 1.9676682353019714
      },
      {
        "epoch": 7,
        "loss": 1.9790417507513245,
        "loss_state": 0.9519630928537739,
        "loss_phys": 0.8915285539271226,
        "loss_corr": 0.672327075431596,
        "loss_amp": 1.1042620512976575,
        "loss_tv": 2.898204276810831,
        "lambda_fwd": 0.02,
        "val_loss": 2.9920709558895657,
        "val_state": 1.4722962102719717,
        "val_phys": 0.9996074182646615,
        "val_corr": 0.6299445288521903,
        "val_amp": 1.9146615394524165
      },
      {
        "epoch": 8,
        "loss": 1.9303454996934577,
        "loss_state": 0.9358710250747737,
        "loss_phys": 0.8879353590865633,
        "loss_corr": 0.6381029193081073,
        "loss_amp": 1.0569995570538648,
        "loss_tv": 2.495069007375347,
        "lambda_fwd": 0.02,
        "val_loss": 2.91690508382661,
        "val_state": 1.441369897552899,
        "val_phys": 0.9986019475119454,
        "val_corr": 0.5986960785729545,
        "val_amp": 1.8501646965742111
      },
      {
        "epoch": 9,
        "loss": 1.8985542503755484,
        "loss_state": 0.9254268372236792,
        "loss_phys": 0.8865245811974825,
        "loss_corr": 0.6174740186378137,
        "loss_amp": 1.0240575279762496,
        "loss_tv": 2.240181456750898,
        "lambda_fwd": 0.02,
        "val_loss": 2.8767295948096683,
        "val_state": 1.425281041434833,
        "val_phys": 0.9979973009654454,
        "val_corr": 0.5885563577924456,
        "val_amp": 1.8069449471575874
      },
      {
        "epoch": 10,
        "loss": 1.87486951030902,
        "loss_state": 0.9165802268839595,
        "loss_phys": 0.8864495772034374,
        "loss_corr": 0.6054507333840897,
        "loss_amp": 1.0014340183628139,
        "loss_tv": 2.0468817611238848,
        "lambda_fwd": 0.02,
        "val_loss": 2.8592101335525513,
        "val_state": 1.4181841249976839,
        "val_phys": 0.9981479474476406,
        "val_corr": 0.5887698786599296,
        "val_amp": 1.7838594828333174
      },
      {
        "epoch": 11,
        "loss": 1.857758319199975,
        "loss_state": 0.9087475093443003,
        "loss_phys": 0.887193082873501,
        "loss_corr": 0.597748025139766,
        "loss_amp": 0.9912569006877159,
        "loss_tv": 1.916923900148762,
        "lambda_fwd": 0.02,
        "val_loss": 2.847020366362163,
        "val_state": 1.4131088576146535,
        "val_phys": 0.9981491395405361,
        "val_corr": 0.5896806035723005,
        "val_amp": 1.7677203629698073
      },
      {
        "epoch": 12,
        "loss": 1.8448769725970369,
        "loss_state": 0.9040034804771195,
        "loss_phys": 0.88721677616461,
        "loss_corr": 0.5916426306340232,
        "loss_amp": 0.9781647208911269,
        "loss_tv": 1.852607674563109,
        "lambda_fwd": 0.02,
        "val_loss": 2.8357440318380083,
        "val_state": 1.4088956245354243,
        "val_phys": 0.9978782960346767,
        "val_corr": 0.5892718689782279,
        "val_amp": 1.7516431978770666
      },
      {
        "epoch": 13,
        "loss": 1.8364444099255461,
        "loss_state": 0.9009402732350933,
        "loss_phys": 0.8872533111429927,
        "loss_corr": 0.5877793191084221,
        "loss_amp": 0.9692474692615111,
        "loss_tv": 1.8086015973518144,
        "lambda_fwd": 0.02,
        "val_loss": 2.830871594803674,
        "val_state": 1.4069145768880844,
        "val_phys": 0.9977072136742728,
        "val_corr": 0.5896635481289455,
        "val_amp": 1.7449369409254618
      },
      {
        "epoch": 14,
        "loss": 1.831166399059011,
        "loss_state": 0.8989230901447695,
        "loss_phys": 0.8871985736177929,
        "loss_corr": 0.5854330134035935,
        "loss_amp": 0.9640991856802755,
        "loss_tv": 1.780870044409339,
        "lambda_fwd": 0.02,
        "val_loss": 2.8281296363898685,
        "val_state": 1.4059798589774541,
        "val_phys": 0.9975889921188354,
        "val_corr": 0.5899792398725238,
        "val_amp": 1.740169154746192
      },
      {
        "epoch": 15,
        "loss": 1.8283015276069072,
        "loss_state": 0.8979349856946006,
        "loss_phys": 0.8871027756093154,
        "loss_corr": 0.5841658577990176,
        "loss_amp": 0.9607684105189879,
        "loss_tv": 1.7672268863934188,
        "lambda_fwd": 0.02,
        "val_loss": 2.826848170586995,
        "val_state": 1.4055726400443487,
        "val_phys": 0.9975181477410453,
        "val_corr": 0.5900969505310059,
        "val_amp": 1.7378233798912592
      },
      {
        "epoch": 16,
        "loss": 1.8270384500275796,
        "loss_state": 0.8975729021563459,
        "loss_phys": 0.8870288240375803,
        "loss_corr": 0.5835934432584848,
        "loss_amp": 0.9589478880611818,
        "loss_tv": 1.7611990010560448,
        "lambda_fwd": 0.02,
        "val_loss": 2.826556899717876,
        "val_state": 1.4054836119924272,
        "val_phys": 0.9975021226065499,
        "val_corr": 0.5901390995298114,
        "val_amp": 1.7372575934444154
      }
    ],
    "reference_noise_improved": [
      {
        "epoch": 1,
        "loss": 2.619641019337213,
        "loss_state": 1.0030127461276837,
        "loss_phys": 0.9990236011903677,
        "loss_corr": 0.8826903086989674,
        "loss_amp": 2.822991653164821,
        "loss_tv": 0.8720704441639915,
        "lambda_fwd": 0.003333333333333333,
        "val_loss": 4.33247663293566,
        "val_state": 1.8815192026751382,
        "val_phys": 1.0604835663522993,
        "val_corr": 1.5634109803608485,
        "val_amp": 3.4583449023110524
      },
      {
        "epoch": 2,
        "loss": 2.4241611317022524,
        "loss_state": 1.0331042195434001,
        "loss_phys": 0.9979640974927304,
        "loss_corr": 0.9032507921332744,
        "loss_amp": 1.9889009719464317,
        "loss_tv": 2.0614832479562333,
        "lambda_fwd": 0.006666666666666666,
        "val_loss": 4.05720620070185,
        "val_state": 1.925239452293941,
        "val_phys": 1.0591540847505843,
        "val_corr": 1.3914177843502589,
        "val_amp": 2.4818947230066573
      },
      {
        "epoch": 3,
        "loss": 2.3262286826745786,
        "loss_state": 1.0801715521670099,
        "loss_phys": 0.9966177228671401,
        "loss_corr": 0.925409950427155,
        "loss_amp": 1.3934940170885912,
        "loss_tv": 3.3400645469551655,
        "lambda_fwd": 0.01,
        "val_loss": 4.01183067049299,
        "val_state": 1.949630273239953,
        "val_phys": 1.0599163940974645,
        "val_corr": 1.3410280432019914,
        "val_amp": 2.2470892795494626
      },
      {
        "epoch": 4,
        "loss": 2.312499069455844,
        "loss_state": 1.084089635468241,
        "loss_phys": 0.9964670049610422,
        "loss_corr": 0.9277495590608511,
        "loss_amp": 1.3146943512247569,
        "loss_tv": 3.4517611105050614,
        "lambda_fwd": 0.013333333333333332,
        "val_loss": 4.018399153436933,
        "val_state": 1.9394112484795707,
        "val_phys": 1.0604341796466283,
        "val_corr": 1.348271403993879,
        "val_amp": 2.3010773062705994
      },
      {
        "epoch": 5,
        "loss": 2.302524166320687,
        "loss_state": 1.0764784759549952,
        "loss_phys": 0.9950194145316509,
        "loss_corr": 0.9234547330372369,
        "loss_amp": 1.31283738008186,
        "loss_tv": 3.3516165320552997,
        "lambda_fwd": 0.016666666666666666,
        "val_loss": 4.011353049959455,
        "val_state": 1.9261727929115295,
        "val_phys": 1.0590037958962577,
        "val_corr": 1.3415458032063075,
        "val_amp": 2.3388263838631764
      },
      {
        "epoch": 6,
        "loss": 2.2968986408034366,
        "loss_state": 1.0735331119886085,
        "loss_phys": 0.9931872246870354,
        "loss_corr": 0.9213532885508751,
        "loss_amp": 1.299994945526123,
        "loss_tv": 3.3078912976962416,
        "lambda_fwd": 0.02,
        "val_loss": 4.002620756626129,
        "val_state": 1.9160612204245158,
        "val_phys": 1.0572394558361597,
        "val_corr": 1.328506691115243,
        "val_amp": 2.3616719586508617
      },
      {
        "epoch": 7,
        "loss": 2.288712930323473,
        "loss_state": 1.072703274773128,
        "loss_phys": 0.9913152865509489,
        "loss_corr": 0.9190687279203045,
        "loss_amp": 1.2792750063227183,
        "loss_tv": 3.2854265490574623,
        "lambda_fwd": 0.02,
        "val_loss": 3.990726717880794,
        "val_state": 1.9058300469602858,
        "val_phys": 1.0552494951656886,
        "val_corr": 1.314152785709926,
        "val_amp": 2.3876742678029195
      },
      {
        "epoch": 8,
        "loss": 2.2814135907301263,
        "loss_state": 1.0725646744023507,
        "loss_phys": 0.9894303314721407,
        "loss_corr": 0.916496573989071,
        "loss_amp": 1.2583383570856124,
        "loss_tv": 3.274331875701449,
        "lambda_fwd": 0.02,
        "val_loss": 3.9825843402317593,
        "val_state": 1.8970718256064825,
        "val_phys": 1.0534457308905465,
        "val_corr": 1.3030062743595667,
        "val_amp": 2.415601210934775
      },
      {
        "epoch": 9,
        "loss": 2.274646577550404,
        "loss_state": 1.0719170761642172,
        "loss_phys": 0.9878625905335839,
        "loss_corr": 0.9139612628452813,
        "loss_amp": 1.2416679254218714,
        "loss_tv": 3.2491662786967717,
        "lambda_fwd": 0.02,
        "val_loss": 3.97170923437391,
        "val_state": 1.8891014265162605,
        "val_phys": 1.0517169748033797,
        "val_corr": 1.2907133528164454,
        "val_amp": 2.4316176686968123
      },
      {
        "epoch": 10,
        "loss": 2.269602515804234,
        "loss_state": 1.0716483815392452,
        "loss_phys": 0.9863051976730575,
        "loss_corr": 0.9118601919999764,
        "loss_amp": 1.2284072397360162,
        "loss_tv": 3.2355383510020244,
        "lambda_fwd": 0.02,
        "val_loss": 3.963480634348733,
        "val_state": 1.8823636301926203,
        "val_phys": 1.0503226518630981,
        "val_corr": 1.2813440220696586,
        "val_amp": 2.447348313672202
      },
      {
        "epoch": 11,
        "loss": 2.265638185970819,
        "loss_state": 1.071124930879963,
        "loss_phys": 0.9851737396040959,
        "loss_corr": 0.9100127255738671,
        "loss_amp": 1.2197382218802153,
        "loss_tv": 3.2205730676651,
        "lambda_fwd": 0.02,
        "val_loss": 3.9566576140267506,
        "val_state": 1.8770619673388345,
        "val_phys": 1.0492886986051286,
        "val_corr": 1.2742437209401811,
        "val_amp": 2.4582883545330594
      },
      {
        "epoch": 12,
        "loss": 2.2627763196603574,
        "loss_state": 1.070729256565891,
        "loss_phys": 0.984388006267263,
        "loss_corr": 0.9085793441800929,
        "loss_amp": 1.213666974608578,
        "loss_tv": 3.207439554271413,
        "lambda_fwd": 0.02,
        "val_loss": 3.952324765069144,
        "val_state": 1.8737125439303262,
        "val_phys": 1.0486212798527308,
        "val_corr": 1.269577945981707,
        "val_amp": 2.4653079637459347
      },
      {
        "epoch": 13,
        "loss": 2.260848783735019,
        "loss_state": 1.070500506393945,
        "loss_phys": 0.9839047709507729,
        "loss_corr": 0.9075747906272091,
        "loss_amp": 1.2094254547090673,
        "loss_tv": 3.197948272548505,
        "lambda_fwd": 0.02,
        "val_loss": 3.95022223676954,
        "val_state": 1.8717254527977534,
        "val_phys": 1.0482448169163294,
        "val_corr": 1.2672832693372453,
        "val_amp": 2.4705587114606584
      },
      {
        "epoch": 14,
        "loss": 2.2594687351539955,
        "loss_state": 1.0702727152340448,
        "loss_phys": 0.9836634735562908,
        "loss_corr": 0.9069336581586013,
        "loss_amp": 1.2066248459602469,
        "loss_tv": 3.1881894086723896,
        "lambda_fwd": 0.02,
        "val_loss": 3.949323058128357,
        "val_state": 1.870588168501854,
        "val_phys": 1.0480511018208094,
        "val_corr": 1.2662654944828577,
        "val_amp": 2.4742818815367564
      },
      {
        "epoch": 15,
        "loss": 2.25866278249826,
        "loss_state": 1.0701270192416745,
        "loss_phys": 0.9835443123063045,
        "loss_corr": 0.9065363656229047,
        "loss_amp": 1.2050740007144303,
        "loss_tv": 3.1820833665221486,
        "lambda_fwd": 0.02,
        "val_loss": 3.9487339428492954,
        "val_state": 1.8700054777520043,
        "val_phys": 1.0479511533464705,
        "val_corr": 1.265647598675319,
        "val_amp": 2.4758573600224087
      },
      {
        "epoch": 16,
        "loss": 2.2582999503434595,
        "loss_state": 1.0701040963628399,
        "loss_phys": 0.9834856186340104,
        "loss_corr": 0.9063561443072646,
        "loss_amp": 1.2041637728463357,
        "loss_tv": 3.18107349125307,
        "lambda_fwd": 0.02,
        "val_loss": 3.948539844581059,
        "val_state": 1.8698598593473434,
        "val_phys": 1.0479241354124886,
        "val_corr": 1.265465361731393,
        "val_amp": 2.4761232691151753
      }
    ],
    "tiny_clean_overfit": [
      {
        "epoch": 1,
        "loss": 3.944982647895813,
        "loss_state": 0.8601185381412506,
        "loss_phys": 2.803770899772644,
        "loss_corr": 0.8236706256866455,
        "loss_amp": 7.994374752044678,
        "loss_tv": 0.45395953953266144,
        "lambda_fwd": 0.003333333333333333
      },
      {
        "epoch": 2,
        "loss": 3.5155842304229736,
        "loss_state": 0.8506754636764526,
        "loss_phys": 3.1239289045333862,
        "loss_corr": 0.7697632312774658,
        "loss_amp": 6.625863313674927,
        "loss_tv": 0.5683237612247467,
        "lambda_fwd": 0.006666666666666666
      },
      {
        "epoch": 3,
        "loss": 3.192380905151367,
        "loss_state": 0.84162637591362,
        "loss_phys": 3.3948657512664795,
        "loss_corr": 0.7347458600997925,
        "loss_amp": 5.585000276565552,
        "loss_tv": 0.6890145838260651,
        "lambda_fwd": 0.01
      },
      {
        "epoch": 4,
        "loss": 2.937434196472168,
        "loss_state": 0.8315896987915039,
        "loss_phys": 3.5785011053085327,
        "loss_corr": 0.704224020242691,
        "loss_amp": 4.769960403442383,
        "loss_tv": 0.808064728975296,
        "lambda_fwd": 0.013333333333333332
      },
      {
        "epoch": 5,
        "loss": 2.723365068435669,
        "loss_state": 0.8202957808971405,
        "loss_phys": 3.616158366203308,
        "loss_corr": 0.6754609048366547,
        "loss_amp": 4.099738121032715,
        "loss_tv": 0.9240103363990784,
        "lambda_fwd": 0.016666666666666666
      },
      {
        "epoch": 6,
        "loss": 2.5403153896331787,
        "loss_state": 0.8075331449508667,
        "loss_phys": 3.4899563789367676,
        "loss_corr": 0.6470291316509247,
        "loss_amp": 3.5500136613845825,
        "loss_tv": 1.0367364287376404,
        "lambda_fwd": 0.02
      },
      {
        "epoch": 7,
        "loss": 2.3682280778884888,
        "loss_state": 0.793258011341095,
        "loss_phys": 3.224817395210266,
        "loss_corr": 0.6188744902610779,
        "loss_amp": 3.093559741973877,
        "loss_tv": 1.1448805332183838,
        "lambda_fwd": 0.02
      },
      {
        "epoch": 8,
        "loss": 2.214147448539734,
        "loss_state": 0.7775365114212036,
        "loss_phys": 2.8862797021865845,
        "loss_corr": 0.5910856127738953,
        "loss_amp": 2.7088887691497803,
        "loss_tv": 1.2480254173278809,
        "lambda_fwd": 0.02
      },
      {
        "epoch": 9,
        "loss": 2.074941575527191,
        "loss_state": 0.7604247629642487,
        "loss_phys": 2.5460541248321533,
        "loss_corr": 0.5637529492378235,
        "loss_amp": 2.3804092407226562,
        "loss_tv": 1.3459906578063965,
        "lambda_fwd": 0.02
      },
      {
        "epoch": 10,
        "loss": 1.9489864110946655,
        "loss_state": 0.7420157492160797,
        "loss_phys": 2.2702107429504395,
        "loss_corr": 0.5370173454284668,
        "loss_amp": 2.097698211669922,
        "loss_tv": 1.4388359785079956,
        "lambda_fwd": 0.02
      },
      {
        "epoch": 11,
        "loss": 1.8350686430931091,
        "loss_state": 0.7223939895629883,
        "loss_phys": 2.1038037538528442,
        "loss_corr": 0.5111576914787292,
        "loss_amp": 1.8530054688453674,
        "loss_tv": 1.5263310074806213,
        "lambda_fwd": 0.02
      },
      {
        "epoch": 12,
        "loss": 1.7317601442337036,
        "loss_state": 0.7016713321208954,
        "loss_phys": 2.05574893951416,
        "loss_corr": 0.48661643266677856,
        "loss_amp": 1.6399751901626587,
        "loss_tv": 1.607410192489624,
        "lambda_fwd": 0.02
      },
      {
        "epoch": 13,
        "loss": 1.6372113823890686,
        "loss_state": 0.6799533665180206,
        "loss_phys": 2.089406669139862,
        "loss_corr": 0.46402373909950256,
        "loss_amp": 1.4537261724472046,
        "loss_tv": 1.6812373399734497,
        "lambda_fwd": 0.02
      },
      {
        "epoch": 14,
        "loss": 1.5490206480026245,
        "loss_state": 0.6574389040470123,
        "loss_phys": 2.1253552436828613,
        "loss_corr": 0.444202721118927,
        "loss_amp": 1.2897321581840515,
        "loss_tv": 1.7468129396438599,
        "lambda_fwd": 0.02
      },
      {
        "epoch": 15,
        "loss": 1.4646517038345337,
        "loss_state": 0.6342884004116058,
        "loss_phys": 2.062570571899414,
        "loss_corr": 0.42778903245925903,
        "loss_amp": 1.1448354125022888,
        "loss_tv": 1.8032751679420471,
        "lambda_fwd": 0.02
      },
      {
        "epoch": 16,
        "loss": 1.3839889168739319,
        "loss_state": 0.6108101904392242,
        "loss_phys": 1.827168345451355,
        "loss_corr": 0.41495612263679504,
        "loss_amp": 1.0218610167503357,
        "loss_tv": 1.8507051467895508,
        "lambda_fwd": 0.02
      },
      {
        "epoch": 17,
        "loss": 1.3102482557296753,
        "loss_state": 0.5873055458068848,
        "loss_phys": 1.5355855226516724,
        "loss_corr": 0.402617871761322,
        "loss_amp": 0.9253459870815277,
        "loss_tv": 1.8902178406715393,
        "lambda_fwd": 0.02
      },
      {
        "epoch": 18,
        "loss": 1.2400009036064148,
        "loss_state": 0.5639907866716385,
        "loss_phys": 1.2842960357666016,
        "loss_corr": 0.3889463245868683,
        "loss_amp": 0.8381755352020264,
        "loss_tv": 1.922569215297699,
        "lambda_fwd": 0.02
      },
      {
        "epoch": 19,
        "loss": 1.170512169599533,
        "loss_state": 0.5409097969532013,
        "loss_phys": 1.1107555627822876,
        "loss_corr": 0.3728554844856262,
        "loss_amp": 0.7496033012866974,
        "loss_tv": 1.9467376470565796,
        "lambda_fwd": 0.02
      },
      {
        "epoch": 20,
        "loss": 1.1002808809280396,
        "loss_state": 0.5181535631418228,
        "loss_phys": 0.9921135306358337,
        "loss_corr": 0.3527640998363495,
        "loss_amp": 0.6572758853435516,
        "loss_tv": 1.9626573324203491,
        "lambda_fwd": 0.02
      },
      {
        "epoch": 21,
        "loss": 1.03118696808815,
        "loss_state": 0.4958910048007965,
        "loss_phys": 0.9379087686538696,
        "loss_corr": 0.3247290253639221,
        "loss_amp": 0.5699208974838257,
        "loss_tv": 1.972499430179596,
        "lambda_fwd": 0.02
      },
      {
        "epoch": 22,
        "loss": 0.9619294106960297,
        "loss_state": 0.47438423335552216,
        "loss_phys": 0.9743108451366425,
        "loss_corr": 0.28097331523895264,
        "loss_amp": 0.4879232347011566,
        "loss_tv": 1.978571355342865,
        "lambda_fwd": 0.02
      },
      {
        "epoch": 23,
        "loss": 0.899430125951767,
        "loss_state": 0.45372480154037476,
        "loss_phys": 0.924662709236145,
        "loss_corr": 0.22295603156089783,
        "loss_amp": 0.4442156255245209,
        "loss_tv": 1.9818142652511597,
        "lambda_fwd": 0.02
      },
      {
        "epoch": 24,
        "loss": 0.8534568548202515,
        "loss_state": 0.4339836835861206,
        "loss_phys": 0.6533693969249725,
        "loss_corr": 0.1795201301574707,
        "loss_amp": 0.45119892060756683,
        "loss_tv": 1.9822875261306763,
        "lambda_fwd": 0.02
      },
      {
        "epoch": 25,
        "loss": 0.8174349069595337,
        "loss_state": 0.41541555523872375,
        "loss_phys": 0.5636224150657654,
        "loss_corr": 0.15691784024238586,
        "loss_amp": 0.45255225896835327,
        "loss_tv": 1.9802889823913574,
        "lambda_fwd": 0.02
      },
      {
        "epoch": 26,
        "loss": 0.7837214767932892,
        "loss_state": 0.39808276295661926,
        "loss_phys": 0.5843762457370758,
        "loss_corr": 0.14223229885101318,
        "loss_amp": 0.44014260172843933,
        "loss_tv": 1.9729103446006775,
        "lambda_fwd": 0.02
      },
      {
        "epoch": 27,
        "loss": 0.7468866109848022,
        "loss_state": 0.38193967938423157,
        "loss_phys": 0.47085508704185486,
        "loss_corr": 0.1300080418586731,
        "loss_amp": 0.41787201166152954,
        "loss_tv": 1.9593191146850586,
        "lambda_fwd": 0.02
      },
      {
        "epoch": 28,
        "loss": 0.7115440368652344,
        "loss_state": 0.36706775426864624,
        "loss_phys": 0.4438381493091583,
        "loss_corr": 0.1230153739452362,
        "loss_amp": 0.38322344422340393,
        "loss_tv": 1.9401406049728394,
        "lambda_fwd": 0.02
      },
      {
        "epoch": 29,
        "loss": 0.6765486598014832,
        "loss_state": 0.35347187519073486,
        "loss_phys": 0.4275582432746887,
        "loss_corr": 0.12346765398979187,
        "loss_amp": 0.33519265055656433,
        "loss_tv": 1.9159271717071533,
        "lambda_fwd": 0.02
      },
      {
        "epoch": 30,
        "loss": 0.6481347382068634,
        "loss_state": 0.34128087759017944,
        "loss_phys": 0.4262140989303589,
        "loss_corr": 0.1317705512046814,
        "loss_amp": 0.2932302951812744,
        "loss_tv": 1.888796865940094,
        "lambda_fwd": 0.02
      },
      {
        "epoch": 31,
        "loss": 0.6263557970523834,
        "loss_state": 0.3304217755794525,
        "loss_phys": 0.4542602002620697,
        "loss_corr": 0.1448451280593872,
        "loss_amp": 0.2599945366382599,
        "loss_tv": 1.8603246808052063,
        "lambda_fwd": 0.02
      },
      {
        "epoch": 32,
        "loss": 0.6095661520957947,
        "loss_state": 0.3205057382583618,
        "loss_phys": 0.4317052662372589,
        "loss_corr": 0.1508467197418213,
        "loss_amp": 0.24912109971046448,
        "loss_tv": 1.830960750579834,
        "lambda_fwd": 0.02
      },
      {
        "epoch": 33,
        "loss": 0.590846061706543,
        "loss_state": 0.3114749491214752,
        "loss_phys": 0.43345150351524353,
        "loss_corr": 0.1366356909275055,
        "loss_amp": 0.2459796667098999,
        "loss_tv": 1.8001811504364014,
        "lambda_fwd": 0.02
      },
      {
        "epoch": 34,
        "loss": 0.5735767781734467,
        "loss_state": 0.30336445569992065,
        "loss_phys": 0.48642778396606445,
        "loss_corr": 0.11125653982162476,
        "loss_amp": 0.25082600116729736,
        "loss_tv": 1.7678050994873047,
        "lambda_fwd": 0.02
      },
      {
        "epoch": 35,
        "loss": 0.5593364834785461,
        "loss_state": 0.29598569869995117,
        "loss_phys": 0.4155654013156891,
        "loss_corr": 0.09572646021842957,
        "loss_amp": 0.2605173587799072,
        "loss_tv": 1.7348097562789917,
        "lambda_fwd": 0.02
      },
      {
        "epoch": 36,
        "loss": 0.5484465807676315,
        "loss_state": 0.2896295040845871,
        "loss_phys": 0.4089515954256058,
        "loss_corr": 0.08431628346443176,
        "loss_amp": 0.26786138117313385,
        "loss_tv": 1.7002807259559631,
        "lambda_fwd": 0.02
      },
      {
        "epoch": 37,
        "loss": 0.5366091132164001,
        "loss_state": 0.28399157524108887,
        "loss_phys": 0.4037402272224426,
        "loss_corr": 0.08205053210258484,
        "loss_amp": 0.2592179775238037,
        "loss_tv": 1.663577914237976,
        "lambda_fwd": 0.02
      },
      {
        "epoch": 38,
        "loss": 0.5269326120615005,
        "loss_state": 0.2790152579545975,
        "loss_phys": 0.4236545264720917,
        "loss_corr": 0.0870027244091034,
        "loss_amp": 0.24557748436927795,
        "loss_tv": 1.6260337829589844,
        "lambda_fwd": 0.02
      },
      {
        "epoch": 39,
        "loss": 0.5183731913566589,
        "loss_state": 0.27469196915626526,
        "loss_phys": 0.42503467202186584,
        "loss_corr": 0.08372896909713745,
        "loss_amp": 0.2418568730354309,
        "loss_tv": 1.5881167650222778,
        "lambda_fwd": 0.02
      },
      {
        "epoch": 40,
        "loss": 0.5100952088832855,
        "loss_state": 0.2706944942474365,
        "loss_phys": 0.3912064731121063,
        "loss_corr": 0.08688664436340332,
        "loss_amp": 0.2333606779575348,
        "loss_tv": 1.5511833429336548,
        "lambda_fwd": 0.02
      },
      {
        "epoch": 41,
        "loss": 0.503099724650383,
        "loss_state": 0.2671211287379265,
        "loss_phys": 0.3865460306406021,
        "loss_corr": 0.08519166707992554,
        "loss_amp": 0.22992709279060364,
        "loss_tv": 1.514806091785431,
        "lambda_fwd": 0.02
      },
      {
        "epoch": 42,
        "loss": 0.4966607242822647,
        "loss_state": 0.26389307528734207,
        "loss_phys": 0.40043094754219055,
        "loss_corr": 0.0772637128829956,
        "loss_amp": 0.2316180318593979,
        "loss_tv": 1.4794947504997253,
        "lambda_fwd": 0.02
      },
      {
        "epoch": 43,
        "loss": 0.4902411699295044,
        "loss_state": 0.2608869820833206,
        "loss_phys": 0.3845688998699188,
        "loss_corr": 0.07356169819831848,
        "loss_amp": 0.23002077639102936,
        "loss_tv": 1.4455084800720215,
        "lambda_fwd": 0.02
      },
      {
        "epoch": 44,
        "loss": 0.4848293662071228,
        "loss_state": 0.2582188993692398,
        "loss_phys": 0.38588903844356537,
        "loss_corr": 0.06907865405082703,
        "loss_amp": 0.22972755134105682,
        "loss_tv": 1.4132170677185059,
        "lambda_fwd": 0.02
      },
      {
        "epoch": 45,
        "loss": 0.4798012524843216,
        "loss_state": 0.2558107376098633,
        "loss_phys": 0.38350558280944824,
        "loss_corr": 0.06549510359764099,
        "loss_amp": 0.2287607491016388,
        "loss_tv": 1.38268381357193,
        "lambda_fwd": 0.02
      },
      {
        "epoch": 46,
        "loss": 0.4748488515615463,
        "loss_state": 0.25361689925193787,
        "loss_phys": 0.3795529454946518,
        "loss_corr": 0.0654962956905365,
        "loss_amp": 0.22349391877651215,
        "loss_tv": 1.3536643385887146,
        "lambda_fwd": 0.02
      },
      {
        "epoch": 47,
        "loss": 0.4703643321990967,
        "loss_state": 0.25164950639009476,
        "loss_phys": 0.3750617951154709,
        "loss_corr": 0.06469786167144775,
        "loss_amp": 0.21948930621147156,
        "loss_tv": 1.3263311386108398,
        "lambda_fwd": 0.02
      },
      {
        "epoch": 48,
        "loss": 0.4662918746471405,
        "loss_state": 0.24985472112894058,
        "loss_phys": 0.37091559171676636,
        "loss_corr": 0.06438466906547546,
        "loss_amp": 0.2154865562915802,
        "loss_tv": 1.3009893894195557,
        "lambda_fwd": 0.02
      },
      {
        "epoch": 49,
        "loss": 0.4628186970949173,
        "loss_state": 0.2482125610113144,
        "loss_phys": 0.36538735032081604,
        "loss_corr": 0.06526786088943481,
        "loss_amp": 0.21161337941884995,
        "loss_tv": 1.2772631645202637,
        "lambda_fwd": 0.02
      },
      {
        "epoch": 50,
        "loss": 0.45929065346717834,
        "loss_state": 0.24672877043485641,
        "loss_phys": 0.3654136061668396,
        "loss_corr": 0.06289294362068176,
        "loss_amp": 0.20965279638767242,
        "loss_tv": 1.2549999952316284,
        "lambda_fwd": 0.02
      },
      {
        "epoch": 51,
        "loss": 0.4562106132507324,
        "loss_state": 0.24534137547016144,
        "loss_phys": 0.36467820405960083,
        "loss_corr": 0.06070247292518616,
        "loss_amp": 0.20856939256191254,
        "loss_tv": 1.2344706654548645,
        "lambda_fwd": 0.02
      },
      {
        "epoch": 52,
        "loss": 0.45308418571949005,
        "loss_state": 0.24404742568731308,
        "loss_phys": 0.3540690541267395,
        "loss_corr": 0.06028705835342407,
        "loss_amp": 0.20574668049812317,
        "loss_tv": 1.2156012654304504,
        "lambda_fwd": 0.02
      },
      {
        "epoch": 53,
        "loss": 0.45050017535686493,
        "loss_state": 0.2428983375430107,
        "loss_phys": 0.3563906103372574,
        "loss_corr": 0.059088826179504395,
        "loss_amp": 0.20392806828022003,
        "loss_tv": 1.1981266736984253,
        "lambda_fwd": 0.02
      },
      {
        "epoch": 54,
        "loss": 0.4478420615196228,
        "loss_state": 0.24184320867061615,
        "loss_phys": 0.3501291573047638,
        "loss_corr": 0.05684936046600342,
        "loss_amp": 0.20300570130348206,
        "loss_tv": 1.1817457675933838,
        "lambda_fwd": 0.02
      },
      {
        "epoch": 55,
        "loss": 0.4457204192876816,
        "loss_state": 0.24088604003190994,
        "loss_phys": 0.35232067108154297,
        "loss_corr": 0.05466574430465698,
        "loss_amp": 0.2027617245912552,
        "loss_tv": 1.166922152042389,
        "lambda_fwd": 0.02
      },
      {
        "epoch": 56,
        "loss": 0.4436095952987671,
        "loss_state": 0.2399962916970253,
        "loss_phys": 0.34738197922706604,
        "loss_corr": 0.05380004644393921,
        "loss_amp": 0.20137380063533783,
        "loss_tv": 1.1533714532852173,
        "lambda_fwd": 0.02
      },
      {
        "epoch": 57,
        "loss": 0.44159506261348724,
        "loss_state": 0.23918765038251877,
        "loss_phys": 0.34223759174346924,
        "loss_corr": 0.053571850061416626,
        "loss_amp": 0.19927722215652466,
        "loss_tv": 1.1411564946174622,
        "lambda_fwd": 0.02
      },
      {
        "epoch": 58,
        "loss": 0.4399900585412979,
        "loss_state": 0.2384633645415306,
        "loss_phys": 0.34331099689006805,
        "loss_corr": 0.053353458642959595,
        "loss_amp": 0.19769907742738724,
        "loss_tv": 1.130318284034729,
        "lambda_fwd": 0.02
      },
      {
        "epoch": 59,
        "loss": 0.438275009393692,
        "loss_state": 0.23781539499759674,
        "loss_phys": 0.339541420340538,
        "loss_corr": 0.05261865258216858,
        "loss_amp": 0.1962115243077278,
        "loss_tv": 1.120299756526947,
        "lambda_fwd": 0.02
      },
      {
        "epoch": 60,
        "loss": 0.4368642419576645,
        "loss_state": 0.23722399771213531,
        "loss_phys": 0.34008100628852844,
        "loss_corr": 0.05186724662780762,
        "loss_amp": 0.19518445432186127,
        "loss_tv": 1.1111769676208496,
        "lambda_fwd": 0.02
      },
      {
        "epoch": 61,
        "loss": 0.4355282336473465,
        "loss_state": 0.23668180406093597,
        "loss_phys": 0.33736199140548706,
        "loss_corr": 0.0516587495803833,
        "loss_amp": 0.1938345581293106,
        "loss_tv": 1.103153109550476,
        "lambda_fwd": 0.02
      },
      {
        "epoch": 62,
        "loss": 0.4343355894088745,
        "loss_state": 0.2361949235200882,
        "loss_phys": 0.33401766419410706,
        "loss_corr": 0.05181345343589783,
        "loss_amp": 0.19236396253108978,
        "loss_tv": 1.0959684252738953,
        "lambda_fwd": 0.02
      },
      {
        "epoch": 63,
        "loss": 0.43332503736019135,
        "loss_state": 0.23576075583696365,
        "loss_phys": 0.3332229554653168,
        "loss_corr": 0.05148816108703613,
        "loss_amp": 0.19154681265354156,
        "loss_tv": 1.0895073413848877,
        "lambda_fwd": 0.02
      },
      {
        "epoch": 64,
        "loss": 0.43240292370319366,
        "loss_state": 0.23537184298038483,
        "loss_phys": 0.3323381096124649,
        "loss_corr": 0.05099588632583618,
        "loss_amp": 0.19097094237804413,
        "loss_tv": 1.0836626291275024,
        "lambda_fwd": 0.02
      },
      {
        "epoch": 65,
        "loss": 0.4315655678510666,
        "loss_state": 0.23502007871866226,
        "loss_phys": 0.33220650255680084,
        "loss_corr": 0.05056968331336975,
        "loss_amp": 0.1903751641511917,
        "loss_tv": 1.0784494280815125,
        "lambda_fwd": 0.02
      },
      {
        "epoch": 66,
        "loss": 0.43080590665340424,
        "loss_state": 0.2347107157111168,
        "loss_phys": 0.33160296082496643,
        "loss_corr": 0.05016964673995972,
        "loss_amp": 0.18983158469200134,
        "loss_tv": 1.0739725232124329,
        "lambda_fwd": 0.02
      },
      {
        "epoch": 67,
        "loss": 0.4301515221595764,
        "loss_state": 0.23443551361560822,
        "loss_phys": 0.3302756994962692,
        "loss_corr": 0.0499114990234375,
        "loss_amp": 0.18937429040670395,
        "loss_tv": 1.0699751377105713,
        "lambda_fwd": 0.02
      },
      {
        "epoch": 68,
        "loss": 0.4295913875102997,
        "loss_state": 0.23419760167598724,
        "loss_phys": 0.3292773962020874,
        "loss_corr": 0.04964005947113037,
        "loss_amp": 0.18903591483831406,
        "loss_tv": 1.0666186809539795,
        "lambda_fwd": 0.02
      },
      {
        "epoch": 69,
        "loss": 0.4290996342897415,
        "loss_state": 0.23399466276168823,
        "loss_phys": 0.3288625478744507,
        "loss_corr": 0.04939746856689453,
        "loss_amp": 0.18868260830640793,
        "loss_tv": 1.063693642616272,
        "lambda_fwd": 0.02
      },
      {
        "epoch": 70,
        "loss": 0.42867740988731384,
        "loss_state": 0.2338235080242157,
        "loss_phys": 0.32847723364830017,
        "loss_corr": 0.049154043197631836,
        "loss_amp": 0.18840087950229645,
        "loss_tv": 1.0613170862197876,
        "lambda_fwd": 0.02
      },
      {
        "epoch": 71,
        "loss": 0.42830251157283783,
        "loss_state": 0.23367445170879364,
        "loss_phys": 0.32832464575767517,
        "loss_corr": 0.04896801710128784,
        "loss_amp": 0.18809334188699722,
        "loss_tv": 1.0592313408851624,
        "lambda_fwd": 0.02
      },
      {
        "epoch": 72,
        "loss": 0.42802657186985016,
        "loss_state": 0.23355647921562195,
        "loss_phys": 0.3280877470970154,
        "loss_corr": 0.04880687594413757,
        "loss_amp": 0.18794091790914536,
        "loss_tv": 1.0575814247131348,
        "lambda_fwd": 0.02
      },
      {
        "epoch": 73,
        "loss": 0.42780619859695435,
        "loss_state": 0.23345842212438583,
        "loss_phys": 0.3277577757835388,
        "loss_corr": 0.0486682653427124,
        "loss_amp": 0.18785768747329712,
        "loss_tv": 1.0562665462493896,
        "lambda_fwd": 0.02
      },
      {
        "epoch": 74,
        "loss": 0.4276091903448105,
        "loss_state": 0.23337948322296143,
        "loss_phys": 0.3274993747472763,
        "loss_corr": 0.04861775040626526,
        "loss_amp": 0.18766380846500397,
        "loss_tv": 1.0551698207855225,
        "lambda_fwd": 0.02
      },
      {
        "epoch": 75,
        "loss": 0.4274679273366928,
        "loss_state": 0.23332096636295319,
        "loss_phys": 0.32734693586826324,
        "loss_corr": 0.048579275608062744,
        "loss_amp": 0.18753445148468018,
        "loss_tv": 1.0543031692504883,
        "lambda_fwd": 0.02
      },
      {
        "epoch": 76,
        "loss": 0.4273667335510254,
        "loss_state": 0.2332793027162552,
        "loss_phys": 0.3272012323141098,
        "loss_corr": 0.04854249954223633,
        "loss_amp": 0.1874520257115364,
        "loss_tv": 1.053725004196167,
        "lambda_fwd": 0.02
      },
      {
        "epoch": 77,
        "loss": 0.4272889643907547,
        "loss_state": 0.23324984312057495,
        "loss_phys": 0.32713836431503296,
        "loss_corr": 0.04849356412887573,
        "loss_amp": 0.1873934492468834,
        "loss_tv": 1.0532992780208588,
        "lambda_fwd": 0.02
      },
      {
        "epoch": 78,
        "loss": 0.4272479861974716,
        "loss_state": 0.2332315891981125,
        "loss_phys": 0.3270779401063919,
        "loss_corr": 0.04845806956291199,
        "loss_amp": 0.18738770484924316,
        "loss_tv": 1.0530444383621216,
        "lambda_fwd": 0.02
      },
      {
        "epoch": 79,
        "loss": 0.42721861600875854,
        "loss_state": 0.2332199364900589,
        "loss_phys": 0.32705897092819214,
        "loss_corr": 0.04843446612358093,
        "loss_amp": 0.18737299740314484,
        "loss_tv": 1.0528817176818848,
        "lambda_fwd": 0.02
      },
      {
        "epoch": 80,
        "loss": 0.4272106736898422,
        "loss_state": 0.23321586102247238,
        "loss_phys": 0.32706111669540405,
        "loss_corr": 0.04842686653137207,
        "loss_amp": 0.18737441301345825,
        "loss_tv": 1.0528334081172943,
        "lambda_fwd": 0.02
      }
    ]
  }
}